a2a_storage/README.md
a2a_storage/__init__.py
a2a_storage/context_store.py
a2a_storage/in_memory_context_store.py
a2a_storage/postgres_context_store.py
a2a_storage/sqlite_context_store.py
a2a_storage/storage_factory.py
app/README.md
app/__init__.py
app/database.py
app/endpoints/README.md
app/endpoints/__init__.py
app/endpoints/a2a.py
app/endpoints/authorized.py
app/endpoints/config.py
app/endpoints/conversations.py
app/endpoints/conversations_v2.py
app/endpoints/conversations_v3.py
app/endpoints/feedback.py
app/endpoints/health.py
app/endpoints/info.py
app/endpoints/metrics.py
app/endpoints/models.py
app/endpoints/providers.py
app/endpoints/query.py
app/endpoints/query_v2.py
app/endpoints/rags.py
app/endpoints/rlsapi_v1.py
app/endpoints/root.py
app/endpoints/shields.py
app/endpoints/streaming_query.py
app/endpoints/streaming_query_v2.py
app/endpoints/tools.py
app/main.py
app/routers.py
authentication/README.md
authentication/__init__.py
authentication/api_key_token.py
authentication/interface.py
authentication/jwk_token.py
authentication/k8s.py
authentication/noop.py
authentication/noop_with_token.py
authentication/rh_identity.py
authentication/utils.py
authorization/README.md
authorization/__init__.py
authorization/azure_token_manager.py
authorization/middleware.py
authorization/resolvers.py
cache/README.md
cache/__init__.py
cache/cache.py
cache/cache_error.py
cache/cache_factory.py
cache/in_memory_cache.py
cache/noop_cache.py
cache/postgres_cache.py
cache/sqlite_cache.py
lightspeed_stack-0.4.0.dist-info/METADATA
lightspeed_stack-0.4.0.dist-info/WHEEL
lightspeed_stack-0.4.0.dist-info/entry_points.txt
lightspeed_stack-0.4.0.dist-info/licenses/LICENSE
metrics/README.md
metrics/__init__.py
metrics/utils.py
models/README.md
models/__init__.py
models/cache_entry.py
models/config.py
models/context.py
models/database/README.md
models/database/__init__.py
models/database/base.py
models/database/conversations.py
models/requests.py
models/responses.py
models/rlsapi/README.md
models/rlsapi/__init__.py
models/rlsapi/requests.py
models/rlsapi/responses.py
quota/README.md
quota/__init__.py
quota/cluster_quota_limiter.py
quota/connect_pg.py
lightspeed_stack-0.4.0.dist-info/RECORD
