Metadata-Version: 2.1
Name: lightspeed-stack
Version: 0.4.0
Summary: LLM tooling stack
Keywords: LLM,RAG
Maintainer-Email: =?utf-8?b?UGF2ZWwgVGnFoW5vdnNrw70=?= <tisnik@centrum.cz>
License:                                  Apache License
Classifier: Development Status :: 4 - Beta
Classifier: Topic :: Scientific/Engineering :: Artificial Intelligence
Classifier: Topic :: Software Development
Classifier: Programming Language :: Python :: 3
Classifier: Programming Language :: Python :: 3 :: Only
Classifier: License :: OSI Approved :: Apache Software License
Project-URL: Homepage, https://github.com/lightspeed-core/lightspeed-stack
Project-URL: Issues, https://github.com/lightspeed-core/lightspeed-stack/issues
Requires-Python: <3.14,>=3.12
Requires-Dist: fastapi>=0.115.12
Requires-Dist: uvicorn>=0.34.3
Requires-Dist: kubernetes>=30.1.0
Requires-Dist: llama-stack==0.3.5
Requires-Dist: llama-stack-client==0.3.5
Requires-Dist: rich>=14.0.0
Requires-Dist: cachetools>=6.1.0
Requires-Dist: prometheus-client>=0.22.1
Requires-Dist: starlette>=0.47.1
Requires-Dist: aiohttp>=3.12.14
Requires-Dist: authlib>=1.6.0
Requires-Dist: a2a-sdk<0.4.0,>=0.3.4
Requires-Dist: email-validator>=2.2.0
Requires-Dist: openai>=1.99.9
Requires-Dist: sqlalchemy[asyncio]>=2.0.42
Requires-Dist: aiosqlite>=0.21.0
Requires-Dist: asyncpg>=0.31.0
Requires-Dist: semver<4.0.0
Requires-Dist: jsonpath-ng>=1.6.1
Requires-Dist: psycopg2-binary>=2.9.10
Requires-Dist: litellm>=1.75.5.post1
Requires-Dist: urllib3==2.6.3
Requires-Dist: PyYAML>=6.0.0
Requires-Dist: einops>=0.8.1
Requires-Dist: azure-core>=1.38.0
Requires-Dist: azure-identity
